cages/__init__.py
cages-0.1.0.dist-info/licenses/LICENSE
cages-0.1.0.dist-info/METADATA
cages-0.1.0.dist-info/WHEEL
cages-0.1.0.dist-info/top_level.txt
cages-0.1.0.dist-info/RECORD
